{
  "id": "plastic_bottle",
  "name": "Chai nước nhựa",
  "emoji": "💧",
  "material_badge": "Nhựa (PET)",
  "stages": [
    {
      "title": "Bắt đầu từ dầu mỏ 🛢️",
      "chapter": "Dầu mỏ",
      "kid_text": "Chai nhựa làm từ một loại nhựa tên là PET, mà PET được làm ra từ dầu mỏ dưới lòng đất.",
      "fun_fact": "Nhựa PET trong suốt nên ta nhìn thấy nước bên trong chai."
    },
    {
      "title": "Tạo hạt nhựa PET ⚪",
      "chapter": "Hạt nhựa",
      "kid_text": "Dầu mỏ được chế biến thành những hạt nhựa PET nhỏ xíu, trong veo.",
      "fun_fact": "Một nắm hạt nhựa nhỏ có thể làm ra nhiều chai đấy!"
    },
    {
      "title": "Thổi phồng thành chai 💨",
      "chapter": "Thổi chai",
      "kid_text": "Hạt nhựa được nung mềm thành một ống nhỏ, rồi bơm hơi thổi phồng lên trong khuôn thành hình chai.",
      "fun_fact": "Trước khi thổi, chai chỉ là một ống nhỏ xíu giống ống nghiệm!"
    },
    {
      "title": "Rót nước và đóng nắp 💧",
      "chapter": "Đóng nắp",
      "kid_text": "Chai được rửa sạch, rót nước vào rồi vặn nắp thật kín.",
      "fun_fact": "Nhớ bỏ chai đã dùng vào thùng tái chế để làm ra đồ mới nhé!"
    }
  ],
  "history": "Ngày xưa, người ta đựng nước trong bình bằng đất, gỗ hay thủy tinh, vừa nặng vừa dễ vỡ. Mãi cách đây khoảng vài chục năm, các nhà khoa học mới tìm ra một loại nhựa tên là PET, vừa nhẹ, vừa trong veo lại bền. Nhờ vậy mà chai nước nhựa quen thuộc của chúng ta mới ra đời.",
  "story": "Bạn nhỏ ơi, ngày xưa người ta chỉ đựng nước trong bình bằng đất, gỗ hay thủy tinh, vừa nặng lại vừa dễ vỡ. Mãi đến cách đây khoảng vài chục năm, các nhà khoa học mới tìm ra một loại nhựa đặc biệt tên là PET, vừa trong veo vừa nhẹ tênh, thế là chai nước nhựa ra đời. Loại nhựa này được làm từ dầu mỏ nằm sâu dưới lòng đất. Người ta đem dầu mỏ chế biến thành những hạt nhựa PET nhỏ xíu, trong suốt như hạt thủy tinh. Rồi các hạt ấy được nung cho mềm ra, kéo thành một cái ống bé tí. Trong khuôn, người ta bơm hơi thổi phồng cái ống lên, y như bạn thổi bong bóng, cho đến khi nó thành một chiếc chai xinh xắn. Cuối cùng, chai được rửa thật sạch, rót đầy nước mát rồi vặn nắp kín. Thật kỳ diệu phải không nào, bạn nhỏ."
}
